rexpr/__init__.py
rexpr-1.0.0.dist-info/METADATA
rexpr-1.0.0.dist-info/WHEEL
rexpr-1.0.0.dist-info/licenses/LICENSE
rexpr-1.0.0.dist-info/RECORD
