Metadata-Version: 2.4
Name: rexpr
Version: 1.0.0
Summary: Get the source code string of an expression and optionally evalute it.
Project-URL: Repository, https://github.com/JoniKauf/rexpr
Project-URL: Issues, https://github.com/JoniKauf/rexpr/issues
Author: JoniKauf
License-Expression: MIT
License-File: LICENSE
Classifier: Operating System :: OS Independent
Classifier: Programming Language :: Python :: 3
Requires-Python: >=3.14
